{
"meta":{"test_sets":[],"test_metrics":[],"learn_metrics":[{"best_value":"Min","name":"MultiClass"}],"launch_mode":"Train","parameters":"","iteration_count":100,"learn_sets":["learn"],"name":"experiment"},
"iterations":[
{"learn":[0.6295854681],"iteration":0,"passed_time":0.06459686622,"remaining_time":6.395089756},
{"learn":[0.4956304685],"iteration":1,"passed_time":0.07024793324,"remaining_time":3.442148729},
{"learn":[0.4335571582],"iteration":2,"passed_time":0.07616522723,"remaining_time":2.46267568},
{"learn":[0.3996538724],"iteration":3,"passed_time":0.08250616703,"remaining_time":1.980148009},
{"learn":[0.3816055846],"iteration":4,"passed_time":0.08846296838,"remaining_time":1.680796399},
{"learn":[0.3641633337],"iteration":5,"passed_time":0.09485774331,"remaining_time":1.486104645},
{"learn":[0.3552303013],"iteration":6,"passed_time":0.1006366282,"remaining_time":1.33702949},
{"learn":[0.3481657713],"iteration":7,"passed_time":0.106659354,"remaining_time":1.226582571},
{"learn":[0.3415240168],"iteration":8,"passed_time":0.1120634324,"remaining_time":1.133085817},
{"learn":[0.3349152326],"iteration":9,"passed_time":0.1177039437,"remaining_time":1.059335493},
{"learn":[0.3303825225],"iteration":10,"passed_time":0.1234240397,"remaining_time":0.9986126851},
{"learn":[0.3263480256],"iteration":11,"passed_time":0.1293779308,"remaining_time":0.9487714923},
{"learn":[0.3237637669],"iteration":12,"passed_time":0.1351963164,"remaining_time":0.9047753484},
{"learn":[0.3195077817],"iteration":13,"passed_time":0.1409036577,"remaining_time":0.8655510399},
{"learn":[0.315584093],"iteration":14,"passed_time":0.1469462335,"remaining_time":0.8326953231},
{"learn":[0.3117604985],"iteration":15,"passed_time":0.152417841,"remaining_time":0.8001936652},
{"learn":[0.3105816577],"iteration":16,"passed_time":0.157460555,"remaining_time":0.768778004},
{"learn":[0.3063814806],"iteration":17,"passed_time":0.1628901781,"remaining_time":0.7420552559},
{"learn":[0.3025099247],"iteration":18,"passed_time":0.1685418797,"remaining_time":0.7185206451},
{"learn":[0.3011231167],"iteration":19,"passed_time":0.173883023,"remaining_time":0.6955320919},
{"learn":[0.2984711669],"iteration":20,"passed_time":0.1795051413,"remaining_time":0.675281246},
{"learn":[0.2911451257],"iteration":21,"passed_time":0.1857207138,"remaining_time":0.6584643488},
{"learn":[0.2881837258],"iteration":22,"passed_time":0.1917606787,"remaining_time":0.6419814025},
{"learn":[0.285756632],"iteration":23,"passed_time":0.2082609494,"remaining_time":0.6594930063},
{"learn":[0.2836797986],"iteration":24,"passed_time":0.2310521756,"remaining_time":0.6931565269},
{"learn":[0.2810228412],"iteration":25,"passed_time":0.2411564992,"remaining_time":0.6863684977},
{"learn":[0.2790122321],"iteration":26,"passed_time":0.2469777867,"remaining_time":0.6677547566},
{"learn":[0.2763275357],"iteration":27,"passed_time":0.2524501534,"remaining_time":0.6491575373},
{"learn":[0.2736173277],"iteration":28,"passed_time":0.257985196,"remaining_time":0.6316189283},
{"learn":[0.269675198],"iteration":29,"passed_time":0.26354066,"remaining_time":0.6149282066},
{"learn":[0.2668981452],"iteration":30,"passed_time":0.2694635356,"remaining_time":0.5997736761},
{"learn":[0.2642800816],"iteration":31,"passed_time":0.2752168317,"remaining_time":0.5848357674},
{"learn":[0.2623513724],"iteration":32,"passed_time":0.280871833,"remaining_time":0.5702549336},
{"learn":[0.2616918426],"iteration":33,"passed_time":0.2869076306,"remaining_time":0.5569383418},
{"learn":[0.2578723051],"iteration":34,"passed_time":0.2931367539,"remaining_time":0.5443968286},
{"learn":[0.2564126728],"iteration":35,"passed_time":0.2984239389,"remaining_time":0.5305314469},
{"learn":[0.2539135119],"iteration":36,"passed_time":0.3042243767,"remaining_time":0.5180036684},
{"learn":[0.2535422064],"iteration":37,"passed_time":0.3091184017,"remaining_time":0.5043510765},
{"learn":[0.2522489648],"iteration":38,"passed_time":0.314581619,"remaining_time":0.4920379169},
{"learn":[0.2512106007],"iteration":39,"passed_time":0.3212144816,"remaining_time":0.4818217223},
{"learn":[0.2485716288],"iteration":40,"passed_time":0.3272583689,"remaining_time":0.4709327748},
{"learn":[0.2481325277],"iteration":41,"passed_time":0.3334735335,"remaining_time":0.4605110701},
{"learn":[0.2458243704],"iteration":42,"passed_time":0.3394880744,"remaining_time":0.4500190754},
{"learn":[0.2443883019],"iteration":43,"passed_time":0.3452244174,"remaining_time":0.4393765312},
{"learn":[0.2411474618],"iteration":44,"passed_time":0.3512315739,"remaining_time":0.4292830347},
{"learn":[0.2404867626],"iteration":45,"passed_time":0.3569967387,"remaining_time":0.419083128},
{"learn":[0.2389328086],"iteration":46,"passed_time":0.36247387,"remaining_time":0.40874713},
{"learn":[0.2372389336],"iteration":47,"passed_time":0.3679828688,"remaining_time":0.3986481079},
{"learn":[0.2332061295],"iteration":48,"passed_time":0.3746269066,"remaining_time":0.3899178007},
{"learn":[0.2314522246],"iteration":49,"passed_time":0.3805545668,"remaining_time":0.3805545668},
{"learn":[0.229942378],"iteration":50,"passed_time":0.3866753049,"remaining_time":0.3715115674},
{"learn":[0.2281699008],"iteration":51,"passed_time":0.3921406596,"remaining_time":0.3619759935},
{"learn":[0.2274628521],"iteration":52,"passed_time":0.4001454918,"remaining_time":0.3548460021},
{"learn":[0.2258413938],"iteration":53,"passed_time":0.4070544627,"remaining_time":0.3467500978},
{"learn":[0.2232836322],"iteration":54,"passed_time":0.4125884228,"remaining_time":0.3375723459},
{"learn":[0.2210394196],"iteration":55,"passed_time":0.4186860424,"remaining_time":0.3289676047},
{"learn":[0.2192519104],"iteration":56,"passed_time":0.4249210877,"remaining_time":0.3205545048},
{"learn":[0.2185297443],"iteration":57,"passed_time":0.4315251709,"remaining_time":0.3124837444},
{"learn":[0.2170299758],"iteration":58,"passed_time":0.4410497096,"remaining_time":0.3064921711},
{"learn":[0.2162010915],"iteration":59,"passed_time":0.4499335656,"remaining_time":0.2999557104},
{"learn":[0.2142242144],"iteration":60,"passed_time":0.4587313768,"remaining_time":0.2932872737},
{"learn":[0.2126625768],"iteration":61,"passed_time":0.4679944314,"remaining_time":0.2868352967},
{"learn":[0.2104416298],"iteration":62,"passed_time":0.4750248572,"remaining_time":0.2789828526},
{"learn":[0.2082890837],"iteration":63,"passed_time":0.4817140843,"remaining_time":0.2709641724},
{"learn":[0.2063642775],"iteration":64,"passed_time":0.4885522914,"remaining_time":0.2630666184},
{"learn":[0.2053712026],"iteration":65,"passed_time":0.4965289806,"remaining_time":0.2557876567},
{"learn":[0.2041497278],"iteration":66,"passed_time":0.5045470509,"remaining_time":0.248508249},
{"learn":[0.2021905216],"iteration":67,"passed_time":0.513023337,"remaining_time":0.2414227468},
{"learn":[0.1998458103],"iteration":68,"passed_time":0.5238578851,"remaining_time":0.2353564411},
{"learn":[0.1983256366],"iteration":69,"passed_time":0.5338271734,"remaining_time":0.2287830743},
{"learn":[0.1973879957],"iteration":70,"passed_time":0.5426144528,"remaining_time":0.2216312554},
{"learn":[0.1966915605],"iteration":71,"passed_time":0.5525319981,"remaining_time":0.2148735548},
{"learn":[0.1950155013],"iteration":72,"passed_time":0.5615741519,"remaining_time":0.2077055083},
{"learn":[0.193357039],"iteration":73,"passed_time":0.5705000815,"remaining_time":0.2004459746},
{"learn":[0.1925907465],"iteration":74,"passed_time":0.5805171587,"remaining_time":0.1935057196},
{"learn":[0.1917662892],"iteration":75,"passed_time":0.590337751,"remaining_time":0.1864224477},
{"learn":[0.1903779893],"iteration":76,"passed_time":0.5980183789,"remaining_time":0.1786288664},
{"learn":[0.1891798048],"iteration":77,"passed_time":0.6053582613,"remaining_time":0.1707420737},
{"learn":[0.187944899],"iteration":78,"passed_time":0.6108376174,"remaining_time":0.1623745565},
{"learn":[0.1874387569],"iteration":79,"passed_time":0.6163986704,"remaining_time":0.1540996676},
{"learn":[0.1868510121],"iteration":80,"passed_time":0.6223054876,"remaining_time":0.1459728921},
{"learn":[0.1856004894],"iteration":81,"passed_time":0.6283166646,"remaining_time":0.1379231703},
{"learn":[0.1841579301],"iteration":82,"passed_time":0.6347700441,"remaining_time":0.1300131416},
{"learn":[0.1835896934],"iteration":83,"passed_time":0.6402547607,"remaining_time":0.1219532878},
{"learn":[0.1823785618],"iteration":84,"passed_time":0.6460312438,"remaining_time":0.1140055136},
{"learn":[0.181303826],"iteration":85,"passed_time":0.6518136566,"remaining_time":0.1061091999},
{"learn":[0.1795109112],"iteration":86,"passed_time":0.6572587033,"remaining_time":0.09821107061},
{"learn":[0.1792737138],"iteration":87,"passed_time":0.66240664,"remaining_time":0.09032817819},
{"learn":[0.1774380877],"iteration":88,"passed_time":0.6689303022,"remaining_time":0.08267677892},
{"learn":[0.176356196],"iteration":89,"passed_time":0.6748994446,"remaining_time":0.07498882718},
{"learn":[0.1754329625],"iteration":90,"passed_time":0.6812060657,"remaining_time":0.06737202848},
{"learn":[0.174445563],"iteration":91,"passed_time":0.6869191933,"remaining_time":0.05973210376},
{"learn":[0.1740073605],"iteration":92,"passed_time":0.6924880912,"remaining_time":0.05212275955},
{"learn":[0.1735670633],"iteration":93,"passed_time":0.6978093648,"remaining_time":0.04454102329},
{"learn":[0.1731170108],"iteration":94,"passed_time":0.7035077671,"remaining_time":0.03702672459},
{"learn":[0.1725812316],"iteration":95,"passed_time":0.7089045939,"remaining_time":0.02953769141},
{"learn":[0.1723235483],"iteration":96,"passed_time":0.7146217741,"remaining_time":0.02210170435},
{"learn":[0.1712295401],"iteration":97,"passed_time":0.7205762087,"remaining_time":0.01470563691},
{"learn":[0.1705496774],"iteration":98,"passed_time":0.7260569494,"remaining_time":0.00733390858},
{"learn":[0.1689799694],"iteration":99,"passed_time":0.7325859594,"remaining_time":0}
]}